{
    "rue": "Rue Mage",
    "stops": [
      { "name": "Saint-Denis-Université", "position": 1, "coordinates": {"lat": 48.9430, "lon": 2.3606} },
      { "name": "Basilique de Saint-Denis", "position": 2, "coordinates": {"lat": 48.933892, "lon": 2.359281} },
      { "name": "Saint-Denis-Porte de Paris", "position": 3, "coordinates": {"lat": 48.9281, "lon": 2.3563} },
      { "name": "Carrefour Pleyel", "position": 4, "coordinates": {"lat": 48.9218, "lon": 2.3370} },
      { "name": "Mairie de Saint-Ouen", "position": 5, "coordinates": {"lat": 48.9131, "lon": 2.3342} },
      { "name": "Garibaldi", "position": 6, "coordinates": {"lat": 48.9084, "lon": 2.3330} },
      { "name": "Porte de Saint-Ouen", "position": 7, "coordinates": {"lat": 48.8990, "lon": 2.3299} },
      { "name": "Guy Môquet", "position": 8, "coordinates": {"lat": 48.8924, "lon": 2.3268} },
      { "name": "La Fourche", "position": 9, "coordinates": {"lat": 48.8860, "lon": 2.3289} },
      { "name": "Place de Clichy", "position": 10, "coordinates": {"lat": 48.8835, "lon": 2.3279} },
      { "name": "Liège", "position": 11, "coordinates": {"lat": 48.8788, "lon": 2.3264} },
      { "name": "Saint-Lazare", "position": 12, "coordinates": {"lat": 48.8763, "lon": 2.3258} },
      { "name": "Miromesnil", "position": 13, "coordinates": {"lat": 48.8701, "lon": 2.3168} },
      { "name": "Champs-Élysées-Clemenceau", "position": 14, "coordinates": {"lat": 48.8668, "lon": 2.3141} },
      { "name": "Invalides", "position": 15, "coordinates":  {"lat": 48.8583, "lon": 2.3123} },
      { "name": "Varenne", "position": 16, "coordinates": {"lat": 48.8559, "lon": 2.3120} },
      { "name": "Saint-François-Xavier", "position": 17, "coordinates": {"lat": 48.8527, "lon": 2.3125} },
      { "name": "Duroc", "position": 18, "coordinates": {"lat": 48.8464, "lon": 2.3184} },
      { "name": "Montparnasse-Bienvenüe", "position": 19, "coordinates": {"lat": 48.84308, "lon": 2.32300} },
      { "name": "Gaîté", "position": 20, "coordinates": {"lat": 48.8391, "lon": 2.3230} },
      { "name": "Pernety", "position": 21, "coordinates": {"lat": 48.8345, "lon": 2.3196} },
      { "name": "Plaisance", "position": 22, "coordinates": {"lat": 48.8303, "lon": 2.3130} },
      { "name": "Porte de Vanves", "position": 23, "coordinates": {"lat": 48.8278, "lng": 2.30599} },
      { "name": "Malakoff-Plateau de Vanves", "position": 24, "coordinates": {"lat": 48.8194, "lon": 2.2998} },
      { "name": "Malakoff-Rue Etienne Dolet", "position": 25, "coordinates": {"lat": 48.8135, "lon": 2.2947} },
      { "name": "Châtillon-Montrouge", "position": 26, "coordinates": {"lat": 48.8061, "lon": 2.2928} }
    ]
  }